myhiddenlib/__init__.py
myhiddenlib/core.py
myhiddenlib-0.1.1.dist-info/licenses/LICENSE
myhiddenlib-0.1.1.dist-info/METADATA
myhiddenlib-0.1.1.dist-info/WHEEL
myhiddenlib-0.1.1.dist-info/top_level.txt
myhiddenlib-0.1.1.dist-info/RECORD
