Metadata-Version: 2.4
Name: myhiddenlib
Version: 0.1.1
Summary: My Hidden Utility Library
Home-page: https://github.com/yourname/myhiddenlib
Author: Vitya
Author-email: vitya@example.com
Classifier: Programming Language :: Python :: 3
Requires-Python: >=3.6
License-File: LICENSE
Dynamic: author
Dynamic: author-email
Dynamic: classifier
Dynamic: description
Dynamic: description-content-type
Dynamic: home-page
Dynamic: license-file
Dynamic: requires-python
Dynamic: summary
